[{"name":"Paul","count":2285},{"name":"Matthew","count":927},{"name":"Thomas","count":3871},{"name":"John","count":9703},{"name":"Steven","count":1169},{"name":"Charles","count":3253},{"name":"Francis","count":886},{"name":"Elizabeth","count":2837},{"name":"Patricia","count":990},{"name":"Daniel","count":1707},{"name":"Michael","count":3953},{"name":"Frank","count":1061},{"name":"Alan","count":896},{"name":"Anne","count":1987},{"name":"George","count":2981},{"name":"Joseph","count":2862},{"name":"Kenneth","count":1143},{"name":"Mark","count":1596},{"name":"Mary","count":1767},{"name":"Douglas","count":807},{"name":"Edward","count":2529},{"name":"Roman","count":1663},{"name":"Richard","count":4630},{"name":"Ann","count":2539},{"name":"Jeffrey","count":1168},{"name":"Andrew","count":1538},{"name":"Stephen","count":1844},{"name":"Arthur","count":1074},{"name":"Nancy","count":938},{"name":"Christopher","count":1104},{"name":"David","count":5313},{"name":"Howard","count":897},{"name":"Donald","count":1637},{"name":"Henry","count":1085},{"name":"William","count":6444},{"name":"Philip","count":939},{"name":"James","count":5649},{"name":"Jane","count":921},{"name":"Bruce","count":834},{"name":"Barbara","count":1141},{"name":"Ellen","count":887},{"name":"Susan","count":1630},{"name":"Anthony","count":851},{"name":"Robert","count":7684},{"name":"Martin","count":839},{"name":"Peter","count":2882},{"name":"Jonathan","count":987},{"name":"Marie","count":1252}]